[
    {
        "Nombre": "ABL No. 6 A Beautiful Life Brands for women and men",
        "Género": "for women and men",
        "Valoración": "1.00",
        "Cantidad de valoraciones": "1",
        "Principales acordes": [
            "fruity",
            "floral",
            "sweet",
            "fresh",
            "white floral"
        ],
        "Perfumistas": []
    },
    {
        "Nombre": "Black Rose A Beautiful Life Brands for women",
        "Género": "for women",
        "Valoración": "5.00",
        "Cantidad de valoraciones": "1",
        "Principales acordes": [
            "rose",
            "musky",
            "leather",
            "amber",
            "animalic",
            "powdery",
            "floral",
            "smoky"
        ],
        "Perfumistas": []
    },
    {
        "Nombre": "Composition by ABL A Beautiful Life Brands for women and men",
        "Género": "for women and men",
        "Valoración": "3.67",
        "Cantidad de valoraciones": "3",
        "Principales acordes": [
            "fruity",
            "mineral",
            "fresh",
            "green",
            "paper"
        ],
        "Perfumistas": []
    },
    {
        "Nombre": "Crush'd A Beautiful Life Brands for women and men",
        "Género": "for women and men",
        "Valoración": "4.67",
        "Cantidad de valoraciones": "3",
        "Principales acordes": [
            "citrus",
            "vanilla",
            "sweet",
            "fresh spicy",
            "fruity"
        ],
        "Perfumistas": []
    },
    {
        "Nombre": "Fawn A Beautiful Life Brands for women and men",
        "Género": "for women and men",
        "Valoración": "3.33",
        "Cantidad de valoraciones": "3",
        "Principales acordes": [
            "sweet",
            "yellow floral",
            "citrus",
            "powdery",
            "bitter",
            "fresh spicy",
            "aromatic",
            "herbal",
            "green"
        ],
        "Perfumistas": []
    },
    {
        "Nombre": "I Heart Unicorns A Beautiful Life Brands for women",
        "Género": "for women",
        "Valoración": "4.11",
        "Cantidad de valoraciones": "9",
        "Principales acordes": [
            "woody",
            "citrus",
            "aromatic",
            "fresh spicy",
            "amber",
            "green",
            "warm spicy",
            "powdery",
            "fruity"
        ],
        "Perfumistas": []
    },
    {
        "Nombre": "Mermaid's Kiss A Beautiful Life Brands for women",
        "Género": "for women",
        "Valoración": "2.33",
        "Cantidad de valoraciones": "3",
        "Principales acordes": [
            "woody",
            "fresh spicy",
            "citrus",
            "sweet",
            "aromatic",
            "fruity",
            "white floral",
            "rum",
            "floral",
            "tropical"
        ],
        "Perfumistas": []
    },
    {
        "Nombre": "Error",
        "Género": "Error",
        "Valoración": "Error",
        "Cantidad de valoraciones": "Error",
        "Principales acordes": "Error",
        "Perfumistas": "Error"
    },
    {
        "Nombre": "Other by ABL A Beautiful Life Brands for women and men",
        "Género": "for women and men",
        "Valoración": "2.50",
        "Cantidad de valoraciones": "2",
        "Principales acordes": [
            "cannabis",
            "coffee",
            "warm spicy",
            "aromatic",
            "herbal",
            "green",
            "smoky",
            "honey"
        ],
        "Perfumistas": []
    },
    {
        "Nombre": "PoP by ABL A Beautiful Life Brands for women and men",
        "Género": "for women and men",
        "Valoración": "1.00",
        "Cantidad de valoraciones": "1",
        "Principales acordes": [
            "floral",
            "fruity",
            "aromatic",
            "warm spicy",
            "fresh",
            "soft spicy",
            "sweet",
            "cherry",
            "citrus",
            "powdery"
        ],
        "Perfumistas": []
    },
    {
        "Nombre": "ABL No. 6 A Beautiful Life Brands for women and men",
        "Género": "for women and men",
        "Valoración": "1.00",
        "Cantidad de valoraciones": "1",
        "Principales acordes": [
            "fruity",
            "floral",
            "sweet",
            "fresh",
            "white floral"
        ],
        "Perfumistas": []
    },
    {
        "Nombre": "Error",
        "Género": "Error",
        "Valoración": "Error",
        "Cantidad de valoraciones": "Error",
        "Principales acordes": "Error",
        "Perfumistas": "Error"
    },
    {
        "Nombre": "Error",
        "Género": "Error",
        "Valoración": "Error",
        "Cantidad de valoraciones": "Error",
        "Principales acordes": "Error",
        "Perfumistas": "Error"
    },
    {
        "Nombre": "Error",
        "Género": "Error",
        "Valoración": "Error",
        "Cantidad de valoraciones": "Error",
        "Principales acordes": "Error",
        "Perfumistas": "Error"
    },
    {
        "Nombre": "Error",
        "Género": "Error",
        "Valoración": "Error",
        "Cantidad de valoraciones": "Error",
        "Principales acordes": "Error",
        "Perfumistas": "Error"
    },
    {
        "Nombre": "I Heart Unicorns A Beautiful Life Brands for women",
        "Género": "for women",
        "Valoración": "4.11",
        "Cantidad de valoraciones": "9",
        "Principales acordes": [
            "woody",
            "citrus",
            "aromatic",
            "fresh spicy",
            "amber",
            "green",
            "warm spicy",
            "powdery",
            "fruity"
        ],
        "Perfumistas": []
    },
    {
        "Nombre": "Error",
        "Género": "Error",
        "Valoración": "Error",
        "Cantidad de valoraciones": "Error",
        "Principales acordes": "Error",
        "Perfumistas": "Error"
    },
    {
        "Nombre": "ABL No. 6 A Beautiful Life Brands for women and men",
        "Género": "for women and men",
        "Valoración": "1.00",
        "Cantidad de valoraciones": "1",
        "Principales acordes": [
            "fruity",
            "floral",
            "sweet",
            "fresh",
            "white floral"
        ],
        "Perfumistas": []
    },
    {
        "Nombre": "Black Rose A Beautiful Life Brands for women",
        "Género": "for women",
        "Valoración": "5.00",
        "Cantidad de valoraciones": "1",
        "Principales acordes": [
            "rose",
            "musky",
            "leather",
            "amber",
            "animalic",
            "powdery",
            "floral",
            "smoky"
        ],
        "Perfumistas": []
    },
    {
        "Nombre": "Composition by ABL A Beautiful Life Brands for women and men",
        "Género": "for women and men",
        "Valoración": "3.67",
        "Cantidad de valoraciones": "3",
        "Principales acordes": [
            "fruity",
            "mineral",
            "fresh",
            "green",
            "paper"
        ],
        "Perfumistas": []
    },
    {
        "Nombre": "Crush'd A Beautiful Life Brands for women and men",
        "Género": "for women and men",
        "Valoración": "4.67",
        "Cantidad de valoraciones": "3",
        "Principales acordes": [
            "citrus",
            "vanilla",
            "sweet",
            "fresh spicy",
            "fruity"
        ],
        "Perfumistas": []
    },
    {
        "Nombre": "Fawn A Beautiful Life Brands for women and men",
        "Género": "for women and men",
        "Valoración": "3.33",
        "Cantidad de valoraciones": "3",
        "Principales acordes": [
            "sweet",
            "yellow floral",
            "citrus",
            "powdery",
            "bitter",
            "fresh spicy",
            "aromatic",
            "herbal",
            "green"
        ],
        "Perfumistas": []
    },
    {
        "Nombre": "I Heart Unicorns A Beautiful Life Brands for women",
        "Género": "for women",
        "Valoración": "4.11",
        "Cantidad de valoraciones": "9",
        "Principales acordes": [
            "woody",
            "citrus",
            "aromatic",
            "fresh spicy",
            "amber",
            "green",
            "warm spicy",
            "powdery",
            "fruity"
        ],
        "Perfumistas": []
    },
    {
        "Nombre": "Mermaid's Kiss A Beautiful Life Brands for women",
        "Género": "for women",
        "Valoración": "2.33",
        "Cantidad de valoraciones": "3",
        "Principales acordes": [
            "woody",
            "fresh spicy",
            "citrus",
            "sweet",
            "aromatic",
            "fruity",
            "white floral",
            "rum",
            "floral",
            "tropical"
        ],
        "Perfumistas": []
    },
    {
        "Nombre": "Error",
        "Género": "Error",
        "Valoración": "Error",
        "Cantidad de valoraciones": "Error",
        "Principales acordes": "Error",
        "Perfumistas": "Error"
    },
    {
        "Nombre": "Other by ABL A Beautiful Life Brands for women and men",
        "Género": "for women and men",
        "Valoración": "2.50",
        "Cantidad de valoraciones": "2",
        "Principales acordes": [
            "cannabis",
            "coffee",
            "warm spicy",
            "aromatic",
            "herbal",
            "green",
            "smoky",
            "honey"
        ],
        "Perfumistas": []
    },
    {
        "Nombre": "PoP by ABL A Beautiful Life Brands for women and men",
        "Género": "for women and men",
        "Valoración": "1.00",
        "Cantidad de valoraciones": "1",
        "Principales acordes": [
            "floral",
            "fruity",
            "aromatic",
            "warm spicy",
            "fresh",
            "soft spicy",
            "sweet",
            "cherry",
            "citrus",
            "powdery"
        ],
        "Perfumistas": []
    },
    {
        "name": "ABL No. 6 A Beautiful Life Brands for women and men",
        "gender": "for women and men",
        "rating_value": "1.00"
    },
    {
        "name": "Black Rose A Beautiful Life Brands for women",
        "gender": "for women",
        "rating_value": "5.00"
    },
    {
        "name": "Composition by ABL A Beautiful Life Brands for women and men",
        "gender": "for women and men",
        "rating_value": "3.67"
    },
    {
        "name": "Crush'd A Beautiful Life Brands for women and men",
        "gender": "for women and men",
        "rating_value": "4.67"
    },
    {
        "name": "Fawn A Beautiful Life Brands for women and men",
        "gender": "for women and men",
        "rating_value": "3.33"
    },
    {
        "name": "I Heart Unicorns A Beautiful Life Brands for women",
        "gender": "for women",
        "rating_value": "4.11"
    },
    {
        "name": "Mermaid's Kiss A Beautiful Life Brands for women",
        "gender": "for women",
        "rating_value": "2.33"
    },
    {},
    {
        "name": "Other by ABL A Beautiful Life Brands for women and men",
        "gender": "for women and men",
        "rating_value": "2.50"
    },
    {
        "name": "PoP by ABL A Beautiful Life Brands for women and men",
        "gender": "for women and men",
        "rating_value": "1.00"
    },
    {},
    {},
    {},
    {},
    {},
    {
        "name": "Gold Rush A Dozen Roses for women",
        "gender": "for women",
        "rating_value": "3.93"
    },
    {
        "name": "Iced White A Dozen Roses for women",
        "gender": "for women",
        "rating_value": "3.56"
    },
    {
        "name": "Shakespeare in Love A Dozen Roses for women",
        "gender": "for women",
        "rating_value": "3.62"
    },
    {},
    {
        "name": "Moonlight Cypress A La Lune for women and men",
        "gender": "for women and men",
        "rating_value": "3.00"
    },
    {
        "name": "Santal Extreme A La Lune for women and men",
        "gender": "for women and men",
        "rating_value": "4.50"
    },
    {
        "name": "Trinity Blood A La Lune for women and men",
        "gender": "for women and men",
        "rating_value": "1.40"
    },
    {
        "name": "Rouge A La Russe for women",
        "gender": "for women",
        "rating_value": "4.12"
    },
    {
        "name": "Almost Transparent Blue A Lab on Fire for women and men",
        "gender": "for women and men",
        "rating_value": "3.83"
    },
    {
        "name": "Hallucinogenic Pearl A Lab on Fire for women and men",
        "gender": "for women and men",
        "rating_value": "3.68"
    },
    {},
    {
        "name": "Liquidnight A Lab on Fire for women and men",
        "gender": "for women and men",
        "rating_value": "4.15"
    },
    {
        "name": "My Own Private Teahupo'o A Lab on Fire for women and men",
        "gender": "for women and men",
        "rating_value": "3.93"
    },
    {
        "name": "Oxymusc A Lab on Fire for women and men",
        "gender": "for women and men",
        "rating_value": "3.07"
    },
    {
        "name": "Rose Rebelle A Lab on Fire for women",
        "gender": "for women",
        "rating_value": "2.98"
    },
    {
        "name": "Rose Rebelle Respawn A Lab on Fire for women",
        "gender": "for women",
        "rating_value": "3.69"
    },
    {
        "name": "Green A Perfume Organic for women and men",
        "gender": "for women and men",
        "rating_value": "3.90"
    },
    {
        "name": "Mejica A Perfume Organic for women and men",
        "gender": "for women and men",
        "rating_value": "4.07"
    },
    {
        "name": "Perfumed Wine - Rosé A Perfume Organic for women and men",
        "gender": "for women and men",
        "rating_value": "3.78"
    },
    {
        "name": "Urban Organic A Perfume Organic for women and men",
        "gender": "for women and men",
        "rating_value": "3.40"
    },
    {
        "name": "White Magik A Perfume Organic for women and men",
        "gender": "for women and men",
        "rating_value": "3.33"
    },
    {},
    {},
    {
        "name": "Filoli Rose A Wing & A Prayer Perfumes for women",
        "gender": "for women",
        "rating_value": "4.00"
    },
    {
        "name": "Haight & Ashbury A Wing & A Prayer Perfumes for women and men",
        "gender": "for women and men",
        "rating_value": "4.00"
    },
    {
        "name": "HOLLY wOUD & VINE A Wing & A Prayer Perfumes for women and men",
        "gender": "for women and men",
        "rating_value": "4.50"
    },
    {},
    {},
    {},
    {},
    {
        "name": "CHANG'E Perfume A Wing & A Prayer Perfumes for women",
        "gender": "for women",
        "rating_value": "4.50"
    },
    {},
    {},
    {
        "name": "La Isla del Sol A Wing & A Prayer Perfumes for women and men",
        "gender": "for women and men",
        "rating_value": "2.00"
    },
    {},
    {
        "name": "SkyDancer A Wing & A Prayer Perfumes for men",
        "gender": "for men",
        "rating_value": "5.00"
    },
    {},
    {},
    {},
    {},
    {},
    {
        "name": "Lemon Ice A Wing & A Prayer Perfumes for women and men",
        "gender": "for women and men",
        "rating_value": "3.00"
    },
    {},
    {},
    {},
    {
        "name": "Sabra CoCo A Wing & A Prayer Perfumes for women and men",
        "gender": "for women and men",
        "rating_value": "3.50"
    },
    {
        "name": "Tea and Lemon A Wing & A Prayer Perfumes for women and men",
        "gender": "for women and men",
        "rating_value": "4.00"
    },
    {},
    {
        "name": "Flowers A Wing & A Prayer Perfumes for women",
        "gender": "for women",
        "rating_value": "5.00"
    },
    {
        "name": "Honeysuckle Rose A Wing & A Prayer Perfumes for women",
        "gender": "for women",
        "rating_value": "4.50"
    },
    {},
    {},
    {},
    {
        "name": "Summer Afternoon A Wing & A Prayer Perfumes for women and men",
        "gender": "for women and men",
        "rating_value": "5.00"
    },
    {},
    {},
    {},
    {},
    {},
    {},
    {},
    {},
    {},
    {
        "name": "Shalott Rose A Wing & A Prayer Perfumes for women",
        "gender": "for women",
        "rating_value": "4.00"
    },
    {},
    {
        "name": "ODR-211 Lucent A-chromiq for women and men",
        "gender": "for women and men",
        "rating_value": "3.50"
    },
    {
        "name": "ODR-212 Florescent A-chromiq for women and men",
        "gender": "for women and men",
        "rating_value": "3.67"
    },
    {
        "name": "ODR-213 Opaque A-chromiq for women and men",
        "gender": "for women and men",
        "rating_value": "4.00"
    },
    {
        "name": "FL/18 A. N. OTHER for women and men",
        "gender": "for women and men",
        "rating_value": "3.96"
    },
    {
        "name": "FR/18 A. N. OTHER for women and men",
        "gender": "for women and men",
        "rating_value": "4.12"
    },
    {
        "name": "OR/18 A. N. OTHER for women and men",
        "gender": "for women and men",
        "rating_value": "4.14"
    },
    {},
    {},
    {},
    {},
    {},
    {},
    {},
    {},
    {},
    {},
    {},
    {
        "name": "ABL No. 6 A Beautiful Life Brands for women and men",
        "gender": "for women and men",
        "rating_value": "1.00"
    },
    {
        "name": "Black Rose A Beautiful Life Brands for women",
        "gender": "for women",
        "rating_value": "5.00"
    },
    {
        "name": "Composition by ABL A Beautiful Life Brands for women and men",
        "gender": "for women and men",
        "rating_value": "3.67"
    },
    {
        "name": "Crush'd A Beautiful Life Brands for women and men",
        "gender": "for women and men",
        "rating_value": "4.67"
    },
    {
        "name": "Fawn A Beautiful Life Brands for women and men",
        "gender": "for women and men",
        "rating_value": "3.33"
    },
    {
        "name": "I Heart Unicorns A Beautiful Life Brands for women",
        "gender": "for women",
        "rating_value": "4.11"
    },
    {
        "name": "Mermaid's Kiss A Beautiful Life Brands for women",
        "gender": "for women",
        "rating_value": "2.33"
    },
    {},
    {
        "name": "Other by ABL A Beautiful Life Brands for women and men",
        "gender": "for women and men",
        "rating_value": "2.50"
    },
    {
        "name": "PoP by ABL A Beautiful Life Brands for women and men",
        "gender": "for women and men",
        "rating_value": "1.00"
    },
    {},
    {},
    {}
]